autosubmit/__init__.py
autosubmit/autosubmit.py
autosubmit/config/config_common.py
autosubmit/database/__init__.py
autosubmit/database/db_common.py
autosubmit/database/db_manager.py
autosubmit/database/db_structure.py
autosubmit/database/data/autosubmit.sql
autosubmit/experiment/__init__.py
autosubmit/experiment/detail_updater.py
autosubmit/experiment/experiment_common.py
autosubmit/git/__init__.py
autosubmit/git/autosubmit_git.py
autosubmit/helpers/__init__.py
autosubmit/helpers/autosubmit_helper.py
autosubmit/helpers/data_transfer.py
autosubmit/helpers/parameters.py
autosubmit/helpers/processes.py
autosubmit/helpers/utils.py
autosubmit/history/__init__.py
autosubmit/history/experiment_history.py
autosubmit/history/experiment_status.py
autosubmit/history/internal_logging.py
autosubmit/history/strategies.py
autosubmit/history/utils.py
autosubmit/history/data_classes/__init__.py
autosubmit/history/data_classes/experiment_run.py
autosubmit/history/data_classes/job_data.py
autosubmit/history/database_managers/__init__.py
autosubmit/history/database_managers/database_manager.py
autosubmit/history/database_managers/database_models.py
autosubmit/history/database_managers/experiment_history_db_manager.py
autosubmit/history/database_managers/experiment_status_db_manager.py
autosubmit/history/platform_monitor/__init__.py
autosubmit/history/platform_monitor/platform_monitor.py
autosubmit/history/platform_monitor/platform_utils.py
autosubmit/history/platform_monitor/slurm_monitor.py
autosubmit/history/platform_monitor/slurm_monitor_item.py
autosubmit/history/platform_monitor/output_examples/__init__.py
autosubmit/job/__init__.py
autosubmit/job/job.py
autosubmit/job/job_common.py
autosubmit/job/job_dict.py
autosubmit/job/job_grouping.py
autosubmit/job/job_list.py
autosubmit/job/job_list_persistence.py
autosubmit/job/job_package_persistence.py
autosubmit/job/job_packager.py
autosubmit/job/job_packages.py
autosubmit/job/job_utils.py
autosubmit/job/metrics_processor.py
autosubmit-4.1.15.dist-info/licenses/LICENSE
autosubmit-4.1.15.dist-info/METADATA
autosubmit-4.1.15.dist-info/WHEEL
autosubmit-4.1.15.dist-info/entry_points.txt
autosubmit-4.1.15.dist-info/top_level.txt
autosubmit-4.1.15.dist-info/RECORD
