Metadata-Version: 2.4
Name: autosubmit
Version: 4.1.15
Summary: Autosubmit is a Python-based workflow manager to create, manage and monitor complex tasks involving different substeps, such as scientific computational experiments. These workflows may involve multiple computing systems for their completion, from HPCs to post-processing clusters or workstations. Autosubmit can orchestrate all the tasks integrating the workflow by managing their dependencies, interfacing with all the platforms involved, and handling eventual errors.
Author-email: "The Autosubmit Team - Models and Workflows Team (MWT) - Barcelona Supercomputing Center (BSC)" <support-autosubmit@bsc.es>
Maintainer-email: "The Autosubmit Team - Models and Workflows Team (MWT) - Barcelona Supercomputing Center (BSC)" <support-autosubmit@bsc.es>
License:                     GNU GENERAL PUBLIC LICENSE
Project-URL: Homepage, https://www.bsc.es/projects/earthscience/autosubmit/
Project-URL: Documentation, https://autosubmit.readthedocs.io/
Project-URL: Download Link, https://earth.bsc.es/wiki/doku.php?id=tools:autosubmit
Keywords: climate,weather,workflow,HPC
Classifier: Programming Language :: Python :: 3.9
Classifier: Programming Language :: Python :: 3.10
Classifier: Programming Language :: Python :: 3.11
Classifier: Programming Language :: Python :: 3.12
Classifier: License :: OSI Approved :: GNU General Public License (GPL)
Classifier: Operating System :: POSIX :: Linux
Requires-Python: <3.13,>=3.9
License-File: LICENSE
Requires-Dist: xlib==0.21
Requires-Dist: bscearth.utils<=0.5.2
Requires-Dist: requests<=2.32.4
Requires-Dist: networkx<=3.2.1
Requires-Dist: portalocker<=3.2.0
Requires-Dist: paramiko>=3.5.0
Requires-Dist: pyparsing==3.2.3
Requires-Dist: matplotlib<=3.9.4
Requires-Dist: typing_extensions==4.*
Requires-Dist: psutil<=7.0.0
Requires-Dist: py3dotplus==1.1.0
Requires-Dist: numpy<3
Requires-Dist: rocrate==0.*
Requires-Dist: autosubmitconfigparser==1.0.79
Requires-Dist: configparser
Requires-Dist: setproctitle
Requires-Dist: invoke>=2.0
Provides-Extra: postgres
Requires-Dist: psycopg2; extra == "postgres"
Provides-Extra: tests
Requires-Dist: pytest<8.5,>=8.2; extra == "tests"
Requires-Dist: pytest-cov; extra == "tests"
Requires-Dist: pytest-mock; extra == "tests"
Requires-Dist: ruff==0.11.13; extra == "tests"
Requires-Dist: pytest-xdist; extra == "tests"
Requires-Dist: testcontainers; extra == "tests"
Provides-Extra: docs
Requires-Dist: livereload; extra == "docs"
Requires-Dist: pydata-sphinx-theme<0.17,>=0.15; extra == "docs"
Requires-Dist: sphinx<9,>=5; extra == "docs"
Requires-Dist: sphinx-autobuild<2024.11,>=2021.3; extra == "docs"
Requires-Dist: sphinx_rtd_theme; extra == "docs"
Requires-Dist: sphinx-reredirects==0.1.*; extra == "docs"
Provides-Extra: all
Requires-Dist: autosubmit[tests]; extra == "all"
Requires-Dist: autosubmit[docs]; extra == "all"
Dynamic: license-file
